eflomal.cpython-311-darwin.so
eflomal-0.1.data/scripts/align.py
eflomal-0.1.data/scripts/makepriors.py
eflomal-0.1.data/scripts/mergefiles.py
eflomal-0.1.dist-info/LICENSE
eflomal-0.1.dist-info/METADATA
eflomal-0.1.dist-info/WHEEL
eflomal-0.1.dist-info/top_level.txt
eflomal-0.1.dist-info/RECORD
