Metadata-Version: 2.1
Name: eflomal
Version: 0.1
Summary: pip installable eflomal
Home-page: https://github.com/robertostling/eflomal
Author: Robert Östling
License: GNU GPLv3
License-File: LICENSE
Requires-Dist: numpy
Requires-Dist: Cython
